{
  "Arn": "arn:aws:cloudformation:us-east-1::type/resource/c830e97710da0c9954d80ba8df021e5439e7134b/Cloudflare-LoadBalancer-Pool",
  "Type": "RESOURCE",
  "TypeName": "Cloudflare::LoadBalancer::Pool",
  "Description": "A resource to manage a pool of origin servers",
  "Schema": "{\n    \"typeName\": \"Cloudflare::LoadBalancer::Pool\",\n    \"description\": \"A resource to manage a pool of origin servers\",\n    \"sourceUrl\": \"https://github.com/aws-ia/cloudformation-cloudflare-resource-providers.git\",\n    \"documentationUrl\": \"https://github.com/aws-ia/cloudformation-cloudflare-resource-providers\",\n    \"typeConfiguration\": {\n        \"properties\": {\n            \"CloudflareAccess\": {\n                \"$ref\": \"#/definitions/CloudflareAccess\"\n            }\n        },\n        \"additionalProperties\": false\n    },\n    \"definitions\": {\n        \"CloudflareAccess\": {\n            \"type\": \"object\",\n            \"properties\": {\n                \"Url\": {\n                    \"type\": \"string\",\n                    \"description\": \"Cloudflare API endpoint\"\n                },\n                \"ApiKey\": {\n                    \"type\": \"string\",\n                    \"description\": \"Cloudflare API tokens are used to authenticate requests to Cloudflare APIs.\"\n                }\n            },\n            \"additionalProperties\": false\n        },\n        \"Origin\": {\n            \"type\": \"object\",\n            \"properties\": {\n                \"Name\": {\n                    \"type\": \"string\"\n                },\n                \"Address\": {\n                    \"type\": \"string\"\n                },\n                \"Enabled\": {\n                    \"type\": \"boolean\"\n                },\n                \"Weight\": {\n                    \"type\": \"number\"\n                }\n            },\n            \"additionalProperties\": false\n        },\n        \"Filter\": {\n            \"description\": \"Filter pool and origin health notifications by resource type or health status. Use null to reset\",\n            \"type\": \"object\",\n            \"properties\": {\n                \"Pool\": {\n                    \"type\": \"object\",\n                    \"properties\": {\n                        \"Healthy\": {\n                            \"type\": \"boolean\"\n                        }\n                    },\n\n                    \"additionalProperties\": false\n                }\n            },\n            \"additionalProperties\": false\n        },\n        \"LoadShedding\": {\n            \"description\": \"Configures load shedding policies and percentages for the pool\",\n            \"type\": \"object\",\n            \"properties\": {\n                \"DefaultPercent\": {\n                    \"type\": \"integer\",\n\t\t    \"description\": \"The percent of traffic to shed from the pool, according to the default policy. Applies to new sessions and traffic without session affinity.\"\n                },\n                \"DefaultPolicy\": {\n                    \"type\": \"string\",\n                    \"description\": \"The default policy to use when load shedding. A random policy randomly sheds a given percent of requests. A hash policy computes a hash over the CF-Connecting-IP address and sheds all requests originating from a percent of IPs.\",\n                    \"enum\": [\"hash\", \"random\"]\n                },\n                \"SessionPercent\": {\n                    \"type\": \"integer\",\n                    \"description\": \"The percent of existing sessions to shed from the pool, according to the session policy.\"\n                },\n                \"SessionPolicy\": {\n                    \"type\": \"string\",\n                    \"description\": \"Session Policy\",\n                    \"enum\": [\"hash\"]\n                }\n            },\n            \"additionalProperties\": false\n        }\n    },\n    \"properties\": {\n        \"Name\": {\n            \"type\": \"string\",\n            \"description\": \"A short name (tag) for the pool. Only alphanumeric characters, hyphens, and underscores are allowed.\",\n            \"pattern\": \"^[a-zA-Z0-9\\\\-\\\\_]+$\"\n        },\n        \"AccountIdentifier\": {\n            \"type\": \"string\",\n            \"description\": \"The account identifier\"\n        },\n        \"Id\": {\n            \"type\": \"string\",\n            \"description\": \"The pool id\"\n        },\n        \"Origins\": {\n            \"description\": \"The list of origins within this pool. Traffic directed at this pool is balanced across all currently healthy origins, provided the pool itself is healthy\",\n            \"type\": \"array\",\n            \"insertionOrder\": false,\n            \"items\": {\n                \"$ref\": \"#/definitions/Origin\"\n            }\n        },\n        \"NotificationFilter\": {\n            \"description\": \"Filter pool and origin health notifications by resource type or health status. Use null to reset\",\n            \"$ref\": \"#/definitions/Filter\"\n        },\n        \"CheckRegions\": {\n            \"description\": \"A list of regions (specified by region code) from which to run health checks. Empty means every Cloudflare data center (the default), but requires an Enterprise plan\",\n            \"type\": \"array\",\n            \"insertionOrder\": false,\n            \"items\": {\n                \"type\": \"string\"\n            }\n        },\n        \"Description\": {\n            \"type\": \"string\",\n            \"description\": \"Free text description.\"\n        },\n        \"Enabled\": {\n            \"type\": \"boolean\",\n            \"description\": \"Whether to enable (the default) this pool. Disabled pools will not receive traffic and are excluded from health checks. Disabling a pool will cause any load balancers using it to failover to the next pool (if any).\"\n        },\n        \"Latitude\": {\n            \"type\": \"number\",\n            \"description\": \"The latitude this pool is physically located at; used for proximity steering. Values should be between -90 and 90.\"\n        },\n        \"Longitude\": {\n            \"type\": \"number\",\n            \"description\": \"The longitude this pool is physically located at; used for proximity steering. Values should be between -180 and 180.\"\n        },\n        \"LoadShedding\": {\n            \"$ref\": \"#/definitions/LoadShedding\"\n        },\n        \"MinimumOrigins\": {\n            \"type\": \"number\",\n            \"description\": \"The minimum number of origins that must be healthy for this pool to serve traffic. If the number of healthy origins falls below this number, the pool will be marked unhealthy and we will failover to the next available pool. Default: 1.\"\n        },\n        \"Monitor\": {\n            \"type\": \"string\",\n            \"description\": \"The ID of the Monitor to use for health checking origins within this pool.\"\n        },\n        \"NotificationEmail\": {\n            \"type\": \"string\",\n            \"description\": \"he email address to send health status notifications to. This can be an individual mailbox or a mailing list. Multiple emails can be supplied as a comma delimited list.\"\n        },\n        \"OriginSteering\": {\n            \"type\": \"object\",\n            \"description\": \"Set an origin steering policy to control origin selection within a pool.\",\n            \"properties\": {\n                \"Policy\": {\n                    \"type\": \"string\",\n                    \"description\": \"The type of origin steering policy to use, either random or hash (based on CF-Connecting-IP).\",\n                    \"enum\": [\"hash\", \"random\"]\n                }\n            },\n            \"additionalProperties\": false\n        },\n        \"CreatedOn\": {\n            \"type\": \"string\",\n            \"description\": \"When the record was last modified\"\n        },\n        \"ModifiedOn\": {\n            \"type\": \"string\",\n            \"description\": \"When the record was last modified\"\n        }\n    },\n    \"additionalProperties\": false,\n    \"tagging\": {\n        \"taggable\": false\n    },\n    \"required\": [\n        \"Name\",\n        \"Origins\"\n    ],\n    \"createOnlyProperties\": [\n        \"/properties/AccountIdentifier\"\n    ],\n    \"readOnlyProperties\": [\n        \"/properties/Id\",\n        \"/properties/CreatedOn\",\n        \"/properties/ModifiedOn\"\n    ],\n    \"primaryIdentifier\": [\n        \"/properties/Id\",\n        \"/properties/AccountIdentifier\"\n    ],\n    \"handlers\": {\n        \"create\": {\n            \"permissions\": []\n        },\n        \"read\": {\n            \"permissions\": []\n        },\n        \"update\": {\n            \"permissions\": []\n        },\n        \"delete\": {\n            \"permissions\": []\n        },\n        \"list\": {\n            \"permissions\": []\n        }\n    }\n}\n",
  "ProvisioningType": "FULLY_MUTABLE",
  "DeprecatedStatus": "LIVE",
  "RequiredActivatedTypes": [],
  "Visibility": "PUBLIC",
  "SourceUrl": "https://github.com/aws-ia/cloudformation-cloudflare-resource-providers.git",
  "DocumentationUrl": "https://github.com/aws-ia/cloudformation-cloudflare-resource-providers",
  "TimeCreated": "2023-12-16T02:30:55.456Z",
  "ConfigurationSchema": "{\n    \"properties\": {\n        \"CloudflareAccess\": {\n            \"$ref\": \"#/definitions/CloudflareAccess\"\n        }\n    },\n    \"additionalProperties\": false,\n    \"definitions\": {\n        \"CloudflareAccess\": {\n            \"type\": \"object\",\n            \"properties\": {\n                \"Url\": {\n                    \"type\": \"string\",\n                    \"description\": \"Cloudflare API endpoint\"\n                },\n                \"ApiKey\": {\n                    \"type\": \"string\",\n                    \"description\": \"Cloudflare API tokens are used to authenticate requests to Cloudflare APIs.\"\n                }\n            },\n            \"additionalProperties\": false\n        },\n        \"Origin\": {\n            \"type\": \"object\",\n            \"properties\": {\n                \"Name\": {\n                    \"type\": \"string\"\n                },\n                \"Address\": {\n                    \"type\": \"string\"\n                },\n                \"Enabled\": {\n                    \"type\": \"boolean\"\n                },\n                \"Weight\": {\n                    \"type\": \"number\"\n                }\n            },\n            \"additionalProperties\": false\n        },\n        \"Filter\": {\n            \"description\": \"Filter pool and origin health notifications by resource type or health status. Use null to reset\",\n            \"type\": \"object\",\n            \"properties\": {\n                \"Pool\": {\n                    \"type\": \"object\",\n                    \"properties\": {\n                        \"Healthy\": {\n                            \"type\": \"boolean\"\n                        }\n                    },\n                    \"additionalProperties\": false\n                }\n            },\n            \"additionalProperties\": false\n        },\n        \"LoadShedding\": {\n            \"description\": \"Configures load shedding policies and percentages for the pool\",\n            \"type\": \"object\",\n            \"properties\": {\n                \"DefaultPercent\": {\n                    \"type\": \"integer\",\n                    \"description\": \"The percent of traffic to shed from the pool, according to the default policy. Applies to new sessions and traffic without session affinity.\"\n                },\n                \"DefaultPolicy\": {\n                    \"type\": \"string\",\n                    \"description\": \"The default policy to use when load shedding. A random policy randomly sheds a given percent of requests. A hash policy computes a hash over the CF-Connecting-IP address and sheds all requests originating from a percent of IPs.\",\n                    \"enum\": [\n                        \"hash\",\n                        \"random\"\n                    ]\n                },\n                \"SessionPercent\": {\n                    \"type\": \"integer\",\n                    \"description\": \"The percent of existing sessions to shed from the pool, according to the session policy.\"\n                },\n                \"SessionPolicy\": {\n                    \"type\": \"string\",\n                    \"description\": \"Session Policy\",\n                    \"enum\": [\n                        \"hash\"\n                    ]\n                }\n            },\n            \"additionalProperties\": false\n        }\n    },\n    \"typeName\": \"Cloudflare::LoadBalancer::Pool\"\n}",
  "PublisherId": "c830e97710da0c9954d80ba8df021e5439e7134b",
  "LatestPublicVersion": "1.1.0",
  "IsActivated": false
}