{
  "Arn": "arn:aws:cloudformation:us-east-1::type/resource/e1238fdd31aee1839e14fb3fb2dac9db154dae29/Generic-Database-Schema",
  "Type": "RESOURCE",
  "TypeName": "Generic::Database::Schema",
  "Description": "Uses the Aurora Data API to execute SQL and enforce a schema within a database cluster. Currently only supports Aurora Postgres.",
  "Schema": "{\n    \"typeName\": \"Generic::Database::Schema\",\n    \"description\": \"Uses the Aurora Data API to execute SQL and enforce a schema within a database cluster. Currently only supports Aurora Postgres.\",\n    \"sourceUrl\": \"https://github.com/iann0036/cfn-types/tree/master/generic-database-schema\",\n    \"definitions\": {\n        \"PrimaryKey\": {\n            \"type\": \"object\",\n            \"properties\": {\n                \"Name\": {\n                    \"description\": \"The name of the primary key. Cannot be updated after creation.\",\n                    \"type\": \"string\",\n                    \"pattern\": \"^[a-zA-Z0-9-_]+$\"\n                },\n                \"Type\": {\n                    \"description\": \"The type of the primary key. Cannot be updated after creation.\",\n                    \"type\": \"string\",\n                    \"pattern\": \"^[a-zA-Z0-9-_]+$\"\n                },\n                \"Default\": {\n                    \"description\": \"The default value of the primary key. Cannot be updated after creation.\",\n                    \"type\": \"string\"\n                }\n            },\n            \"required\": [\n                \"Name\",\n                \"Type\"\n            ],\n            \"additionalProperties\": false\n        },\n        \"Column\": {\n            \"type\": \"object\",\n            \"properties\": {\n                \"Name\": {\n                    \"description\": \"The name of the column. Creates the column if it doesn't exist. Cannot be updated after creation.\",\n                    \"type\": \"string\",\n                    \"pattern\": \"^[a-zA-Z0-9-_]+$\"\n                },\n                \"Type\": {\n                    \"description\": \"The type of the column. Cannot be updated after creation.\",\n                    \"type\": \"string\",\n                    \"pattern\": \"^[a-zA-Z0-9-_]+$\"\n                },\n                \"Nullable\": {\n                    \"description\": \"Whether the column is nullable. Cannot be updated after creation.\",\n                    \"type\": \"boolean\"\n                },\n                \"Default\": {\n                    \"description\": \"The default value of the column. Cannot be updated after creation.\",\n                    \"type\": \"string\"\n                }\n            },\n            \"required\": [\n                \"Name\",\n                \"Type\"\n            ],\n            \"additionalProperties\": false\n        },\n        \"Table\": {\n            \"type\": \"object\",\n            \"properties\": {\n                \"Name\": {\n                    \"description\": \"The name of the table. Creates the table if it doesn't exist.\",\n                    \"type\": \"string\",\n                    \"pattern\": \"^[a-zA-Z0-9-_]+$\"\n                },\n                \"Columns\": {\n                    \"description\": \"An array of columns to manage within the database.\",\n                    \"type\": \"array\",\n                    \"items\": {\n                        \"$ref\": \"#/definitions/Column\"\n                    },\n                    \"insertionOrder\": true\n                },\n                \"PrimaryKey\": {\n                    \"$ref\": \"#/definitions/PrimaryKey\"\n                }\n            },\n            \"required\": [\n                \"Name\"\n            ],\n            \"additionalProperties\": false\n        },\n        \"Database\": {\n            \"type\": \"object\",\n            \"properties\": {\n                \"Name\": {\n                    \"description\": \"The name of the database. Creates the database if it doesn't exist.\",\n                    \"type\": \"string\",\n                    \"pattern\": \"^[a-zA-Z0-9-_]+$\"\n                },\n                \"Tables\": {\n                    \"description\": \"An array of tables to manage within the database.\",\n                    \"type\": \"array\",\n                    \"items\": {\n                        \"$ref\": \"#/definitions/Table\"\n                    },\n                    \"insertionOrder\": true\n                },\n                \"Extensions\": {\n                    \"description\": \"An array of extensions to enable within the database.\",\n                    \"type\": \"array\",\n                    \"items\": {\n                        \"type\": \"string\",\n                        \"pattern\": \"^[a-zA-Z0-9-_]+$\"\n                    },\n                    \"insertionOrder\": true\n                },\n                \"SQL\": {\n                    \"description\": \"An array of SQL statements to execute within the database.\",\n                    \"type\": \"array\",\n                    \"items\": {\n                        \"type\": \"string\"\n                    },\n                    \"insertionOrder\": true\n                }\n            },\n            \"required\": [\n                \"Name\"\n            ],\n            \"additionalProperties\": false\n        },\n        \"User\": {\n            \"type\": \"object\",\n            \"properties\": {\n                \"Name\": {\n                    \"description\": \"The username of the user. Creates the user/role.\",\n                    \"type\": \"string\",\n                    \"pattern\": \"^[a-zA-Z0-9-_]+$\"\n                },\n                \"SecretId\": {\n                    \"description\": \"The Secrets Manager secret ID or ARN of the credentials to set for the user ('password' field of the JSON secret value).\",\n                    \"type\": \"string\"\n                },\n                \"SuperUser\": {\n                    \"description\": \"Whether to give the user rds_superuser privileges.\",\n                    \"type\": \"boolean\"\n                },\n                \"Grants\": {\n                    \"description\": \"An array of grants to assign to the user.\",\n                    \"type\": \"array\",\n                    \"items\": {\n                        \"$ref\": \"#/definitions/Grant\"\n                    },\n                    \"insertionOrder\": true\n                }\n            },\n            \"required\": [\n                \"Name\"\n            ],\n            \"additionalProperties\": false\n        },\n        \"Grant\": {\n            \"type\": \"object\",\n            \"properties\": {\n                \"Database\": {\n                    \"description\": \"The name of the database. If the grant Table field is omitted, this represents a database grant, otherwise represents a table grant.\",\n                    \"type\": \"string\"\n                },\n                \"Table\": {\n                    \"description\": \"The name of the table. The grant Database field must specify the containing database and the database must be specified in the Databases section of the base of the type.\",\n                    \"type\": \"string\"\n                },\n                \"Privileges\": {\n                    \"description\": \"An array of privileges to grant (CONNECT, SELECT, etc.).\",\n                    \"type\": \"array\",\n                    \"items\": {\n                        \"type\": \"string\",\n                        \"pattern\": \"^[a-zA-Z0-9]+$\"\n                    },\n                    \"insertionOrder\": true,\n                    \"minItems\": 1\n                }\n            },\n            \"required\": [\n                \"Database\",\n                \"Privileges\"\n            ],\n            \"additionalProperties\": false\n        }\n    },\n    \"properties\": {\n        \"ExecutionId\": {\n            \"description\": \"A unique identifier to track this execution.\",\n            \"type\": \"string\"\n        },\n        \"ClusterArn\": {\n            \"description\": \"The Amazon Resource Name (ARN) of the Aurora Serverless DB cluster.\",\n            \"type\": \"string\",\n            \"pattern\": \"^arn:.*:rds:.*:.*:cluster:.+$\"\n        },\n        \"SecretArn\": {\n            \"description\": \"The name or ARN of the secret that enables access to the DB cluster.\",\n            \"type\": \"string\"\n        },\n        \"Databases\": {\n            \"description\": \"An array of databases to manage within the cluster.\",\n            \"type\": \"array\",\n            \"items\": {\n                \"$ref\": \"#/definitions/Database\"\n            },\n            \"insertionOrder\": true\n        },\n        \"SQL\": {\n            \"description\": \"An array of SQL statements to execute within the postgres database.\",\n            \"type\": \"array\",\n            \"items\": {\n                \"type\": \"string\"\n            },\n            \"insertionOrder\": true\n        },\n        \"Users\": {\n            \"description\": \"An array of users within the cluster.\",\n            \"type\": \"array\",\n            \"items\": {\n                \"$ref\": \"#/definitions/User\"\n            },\n            \"insertionOrder\": true\n        },\n        \"SQLIdempotency\": {\n            \"description\": \"Whether arbitrary SQL statements are executed once (IDEMPOTENT), or on every update (RUN_ONCE).\",\n            \"type\": \"string\",\n            \"enum\": [\n                \"IDEMPOTENT\",\n                \"RUN_ONCE\"\n            ]\n        }\n    },\n    \"additionalProperties\": false,\n    \"required\": [\n        \"ClusterArn\",\n        \"SecretArn\"\n    ],\n    \"readOnlyProperties\": [\n        \"/properties/ExecutionId\"\n    ],\n    \"writeOnlyProperties\": [\n        \"/properties/ClusterArn\",\n        \"/properties/SecretArn\",\n        \"/properties/Databases\",\n        \"/properties/SQL\",\n        \"/properties/Users\",\n        \"/properties/SQLIdempotency\"\n    ],\n    \"createOnlyProperties\": [\n        \"/properties/ClusterArn\"\n    ],\n    \"primaryIdentifier\": [\n        \"/properties/ExecutionId\"\n    ],\n    \"taggable\": false,\n    \"handlers\": {\n        \"create\": {\n            \"permissions\": [\n                \"rds:DescribeDBClusters\",\n                \"secretsmanager:GetSecretValue\",\n                \"rds-data:ExecuteStatement\",\n                \"rds-data:BeginTransaction\",\n                \"rds-data:CommitTransaction\",\n                \"dynamodb:DescribeTable\",\n                \"dynamodb:CreateTable\",\n                \"dynamodb:PutItem\"\n            ]\n        },\n        \"read\": {\n            \"permissions\": [\n                \"dynamodb:DescribeTable\",\n                \"dynamodb:CreateTable\",\n                \"dynamodb:GetItem\"\n            ]\n        },\n        \"update\": {\n            \"permissions\": [\n                \"rds:DescribeDBClusters\",\n                \"secretsmanager:GetSecretValue\",\n                \"rds-data:ExecuteStatement\",\n                \"rds-data:BeginTransaction\",\n                \"rds-data:CommitTransaction\",\n                \"dynamodb:DescribeTable\",\n                \"dynamodb:CreateTable\",\n                \"dynamodb:UpdateItem\",\n                \"dynamodb:GetItem\"\n            ]\n        },\n        \"delete\": {\n            \"permissions\": [\n                \"dynamodb:DescribeTable\",\n                \"dynamodb:CreateTable\",\n                \"dynamodb:DeleteItem\",\n                \"dynamodb:GetItem\"\n            ]\n        },\n        \"list\": {\n            \"permissions\": [\n                \"dynamodb:DescribeTable\",\n                \"dynamodb:CreateTable\",\n                \"dynamodb:Scan\"\n            ]\n        }\n    }\n}\n",
  "ProvisioningType": "FULLY_MUTABLE",
  "DeprecatedStatus": "LIVE",
  "RequiredActivatedTypes": [],
  "Visibility": "PUBLIC",
  "SourceUrl": "https://github.com/iann0036/cfn-types/tree/master/generic-database-schema",
  "TimeCreated": "2021-06-28T21:45:24.887Z",
  "PublisherId": "e1238fdd31aee1839e14fb3fb2dac9db154dae29",
  "LatestPublicVersion": "1.0.0",
  "IsActivated": false
}